nanami/__init__.py
nanami/client.py
nanami/main.py
nanami/nanami.py
nanami/utils.py
nanami-0.0.5.dist-info/METADATA
nanami-0.0.5.dist-info/WHEEL
nanami-0.0.5.dist-info/entry_points.txt
nanami-0.0.5.dist-info/top_level.txt
nanami-0.0.5.dist-info/RECORD
