Metadata-Version: 2.1
Name: nanami
Version: 0.0.5
Summary: UNKNOWN
Home-page: https://github.com/nanami-ci/client
Author: nanami-ci
Author-email: gray@nanami.io
License: UNKNOWN
Project-URL: Source Code, https://github.com/nanami-ci/client
Platform: any
Requires-Python: >=3.6
Requires-Dist: nvgpu (==0.9.0)
Requires-Dist: docker (==4.4.4)
Requires-Dist: click (==7.1.2)
Requires-Dist: urllib3 (==1.26.4)
Requires-Dist: chardet (==4.0.0)
Requires-Dist: certifi (==2020.12.5)
Requires-Dist: idna (==3.1)
Requires-Dist: typing-extensions (==3.7.4.3)
Requires-Dist: Flask (==1.1.2)
